pylablib_lightweight-1.4.3.dist-info/RECORD
pylablib_lightweight-1.4.3.dist-info/LICENSE
pylablib_lightweight-1.4.3.dist-info/WHEEL
pylablib_lightweight-1.4.3.dist-info/top_level.txt
pylablib_lightweight-1.4.3.dist-info/METADATA
pylablib/aux_libs.py
pylablib/__init__.py
pylablib/widgets.py
pylablib/__main__.py
pylablib/misc/__init__.py
pylablib/misc/file_formats/__init__.py
pylablib/misc/file_formats/cam.py
pylablib/core/__init__.py
pylablib/core/devio/__export__.py
pylablib/core/devio/hid_lib.py
pylablib/core/devio/interface.py
pylablib/core/devio/hid.py
pylablib/core/devio/__init__.py
pylablib/core/devio/SCPI.py
pylablib/core/devio/hid_base.py
pylablib/core/devio/comm_backend.py
pylablib/core/devio/backend_logger.py
pylablib/core/devio/data_format.py
pylablib/core/devio/base.py
pylablib/core/fileio/__export__.py
pylablib/core/fileio/table_stream.py
pylablib/core/fileio/datafile.py
pylablib/core/fileio/dict_entry.py
pylablib/core/fileio/loadfile_utils.py
pylablib/core/fileio/__init__.py
pylablib/core/fileio/location.py
pylablib/core/fileio/savefile.py
pylablib/core/fileio/parse_csv.py
pylablib/core/fileio/loadfile.py
pylablib/core/utils/library_parameters.py
pylablib/core/utils/functions.py
pylablib/core/utils/ctypes_tools.py
pylablib/core/utils/files.py
pylablib/core/utils/__export__.py
pylablib/core/utils/crc.py
pylablib/core/utils/strpack.py
pylablib/core/utils/units.py
pylablib/core/utils/array_utils.py
pylablib/core/utils/ipc.py
pylablib/core/utils/cext_tools.py
pylablib/core/utils/net.py
pylablib/core/utils/funcargparse.py
pylablib/core/utils/py3.py
pylablib/core/utils/__init__.py
pylablib/core/utils/observer_pool.py
pylablib/core/utils/numerical.py
pylablib/core/utils/rpyc_utils.py
pylablib/core/utils/strdump.py
pylablib/core/utils/nbtools.py
pylablib/core/utils/module.py
pylablib/core/utils/string.py
pylablib/core/utils/ctypes_wrap.py
pylablib/core/utils/indexing.py
pylablib/core/utils/dictionary.py
pylablib/core/utils/general.py
pylablib/core/gui/__export__.py
pylablib/core/gui/formatter.py
pylablib/core/gui/__init__.py
pylablib/core/gui/utils.py
pylablib/core/gui/value_handling.py
pylablib/core/gui/limiter.py
