Metadata-Version: 2.1
Name: pylablib-lightweight
Version: 1.4.3
Summary: Code for use in lab environment: experiment automation, data acquisition, device communication
Home-page: https://github.com/AlexShkarin/pyLabLib
Author: Alexey Shkarin
Author-email: pylablib@gmail.com
License: GPLv3
Project-URL: Documentation, https://pylablib.readthedocs.io
Project-URL: Source, https://github.com/AlexShkarin/pyLabLib/
Project-URL: Tracker, https://github.com/AlexShkarin/pyLabLib/issues
Classifier: Development Status :: 4 - Beta
Classifier: Operating System :: Microsoft :: Windows
Classifier: Intended Audience :: Developers
Classifier: Intended Audience :: Science/Research
Classifier: Topic :: Scientific/Engineering
Classifier: License :: OSI Approved :: GNU General Public License v3 (GPLv3)
Classifier: Programming Language :: Python :: 3
Classifier: Programming Language :: Python :: 3.6
Classifier: Programming Language :: Python :: 3.7
Classifier: Programming Language :: Python :: 3.8
Classifier: Programming Language :: Python :: 3.9
Classifier: Programming Language :: Python :: 3.10
Classifier: Programming Language :: Python :: 3.11
Classifier: Programming Language :: Python :: 3.12
License-File: LICENSE
Requires-Dist: numpy
Requires-Dist: scipy
Requires-Dist: pandas
Provides-Extra: devio
Requires-Dist: pyft232 ; extra == 'devio'
Requires-Dist: pyvisa >=1.6 ; extra == 'devio'
Requires-Dist: pyserial ; extra == 'devio'
Requires-Dist: pyusb ; extra == 'devio'
Provides-Extra: devio-full
Requires-Dist: pyft232 ; extra == 'devio-full'
Requires-Dist: pyvisa >=1.6 ; extra == 'devio-full'
Requires-Dist: pyserial ; extra == 'devio-full'
Requires-Dist: pyusb ; extra == 'devio-full'
Requires-Dist: nidaqmx ; extra == 'devio-full'
Requires-Dist: websocket-client ; extra == 'devio-full'
Provides-Extra: extra
Requires-Dist: rpyc ; extra == 'extra'
Requires-Dist: numba ; extra == 'extra'
Provides-Extra: gui-pyqt5
Requires-Dist: pyqt5 >=5.9 ; extra == 'gui-pyqt5'
Requires-Dist: pyqtgraph ; extra == 'gui-pyqt5'
Provides-Extra: gui-pyside2
Requires-Dist: pyside2 ; extra == 'gui-pyside2'
Requires-Dist: shiboken2 ; extra == 'gui-pyside2'
Requires-Dist: pyqtgraph >0.10 ; extra == 'gui-pyside2'
